ndx_hierarchical_behavioral_data/__init__.py
ndx_hierarchical_behavioral_data/hierarchical_behavioral_data.py
ndx_hierarchical_behavioral_data/mocha_io.py
ndx_hierarchical_behavioral_data/text_grid_io.py
ndx_hierarchical_behavioral_data/transcription_io.py
ndx_hierarchical_behavioral_data/definitions/__init__.py
ndx_hierarchical_behavioral_data/definitions/transcription.py
ndx_hierarchical_behavioral_data/spec/ndx-hierarchical-behavioral-data.extensions.yaml
ndx_hierarchical_behavioral_data/spec/ndx-hierarchical-behavioral-data.namespace.yaml
tests/__init__.py
tests/test_hierarchical_behavior_data.py
tests/test_transcription_io.py
ndx_hierarchical_behavioral_data-0.1.2.dist-info/LICENSE.txt
ndx_hierarchical_behavioral_data-0.1.2.dist-info/METADATA
ndx_hierarchical_behavioral_data-0.1.2.dist-info/WHEEL
ndx_hierarchical_behavioral_data-0.1.2.dist-info/top_level.txt
ndx_hierarchical_behavioral_data-0.1.2.dist-info/RECORD
