Metadata-Version: 2.1
Name: ndx-hierarchical-behavioral-data
Version: 0.1.2
Summary: NWB extensions for storing hierarchical behavioral data
Home-page: https://github.com/catalystneuro/ndx-hierarchical-behavioral-data
Author: Ben Dichter
Author-email: ben.dichter@catalystneuro.com
License: BSD 3-Clause
Classifier: Intended Audience :: Developers
Classifier: Intended Audience :: Science/Research
License-File: LICENSE.txt
Requires-Dist: pynwb (>=1.1.2)
